martin_howard_sdk/__init__.py
martin_howard_sdk/admin.py
martin_howard_sdk/apps.py
martin_howard_sdk/forms.py
martin_howard_sdk/models.py
martin_howard_sdk/tests.py
martin_howard_sdk/urls.py
martin_howard_sdk/views.py
martin_howard_sdk/blocks/__init__.py
martin_howard_sdk/blocks/event_block.py
martin_howard_sdk/blocks/heading_block.py
martin_howard_sdk/libs/Tools.py
martin_howard_sdk/libs/__init__.py
martin_howard_sdk/migrations/__init__.py
martin_howard_sdk/models/__init__.py
martin_howard_sdk/tests/__init__.py
martin_howard_sdk/widgets/__init__.py
martin_howard_sdk-0.1.3.dist-info/licenses/LICENSE
martin_howard_sdk-0.1.3.dist-info/METADATA
martin_howard_sdk-0.1.3.dist-info/WHEEL
martin_howard_sdk-0.1.3.dist-info/top_level.txt
martin_howard_sdk-0.1.3.dist-info/RECORD
