Metadata-Version: 2.4
Name: martin_howard_sdk
Version: 0.1.3
Summary: A brief description of your package
Home-page: https://github.com/yourusername/your_package
Author: Martin J. Howard
Author-email: hey@eucon.edu
Classifier: Programming Language :: Python :: 3
Classifier: License :: OSI Approved :: MIT License
Classifier: Operating System :: OS Independent
Requires-Python: >=3.11.7
License-File: LICENSE
Dynamic: author
Dynamic: author-email
Dynamic: classifier
Dynamic: description
Dynamic: description-content-type
Dynamic: home-page
Dynamic: license-file
Dynamic: requires-python
Dynamic: summary
